sca/__init__.py
sca/corpus.py
scolan-0.0.4.dist-info/METADATA
scolan-0.0.4.dist-info/WHEEL
scolan-0.0.4.dist-info/licenses/LICENSE
scolan-0.0.4.dist-info/RECORD
