Metadata-Version: 2.4
Name: scolan
Version: 0.0.4
Summary: An implementation of Structural Collocation Analysis (https://doi.org/10.1080/01615440.2024.2414259)
Project-URL: Homepage, https://github.com/mathjoha/sca
Project-URL: Bug Tracker, https://github.com/mathjoha/sca/issues
Author: Betto van Waarden
Author-email: Mathias Johansson <MathiasJoha@gmail.com>
Maintainer-email: Mathias Johansson <MathiasJoha@gmail.com>
License: Attribution-NonCommercial 4.0 International
License-File: LICENSE
Keywords: collocation,corpus analysis,linguistics
Classifier: Operating System :: OS Independent
Classifier: Programming Language :: Python :: 3
Classifier: Topic :: Scientific/Engineering :: Information Analysis
Classifier: Topic :: Text Processing :: Linguistic
Requires-Python: >=3.8
Requires-Dist: nltk==3.9.1
Requires-Dist: pandas==2.2.3
Requires-Dist: pyyaml==6.0.2
Requires-Dist: sqlite-utils==3.38
Requires-Dist: tqdm==4.67.1
Provides-Extra: dev
Requires-Dist: coverage-badge==1.1.2; extra == 'dev'
Requires-Dist: hatch==1.14.1; extra == 'dev'
Requires-Dist: pytest-cov==6.1.1; extra == 'dev'
Requires-Dist: pytest==8.3.5; extra == 'dev'
Requires-Dist: tox==4.26.0; extra == 'dev'
